README.md
pyproject.toml
setup.cfg
setup.py
steganography_in_text/Crypter.py
steganography_in_text/Decrypter.py
steganography_in_text/__init__.py
steganography_in_text/all_unit_tests.py
steganography_in_text/functions.py
steganography_in_text.egg-info/PKG-INFO
steganography_in_text.egg-info/SOURCES.txt
steganography_in_text.egg-info/dependency_links.txt
steganography_in_text.egg-info/top_level.txt