Metadata-Version: 2.1
Name: steganography-in-text
Version: 0.1.3
Summary: Это модуль, умеющий скрывать текст в тексте
Home-page: https://github.com/red-lexinus/steganography_in_text
Author: Lexinus
Author-email: starshenkov3@gmail.com
License: Apache License, version 2.0, see LICENSE file
Project-URL: Bug Tracker, https://github.com/red-lexinus/steganography_in_text
Platform: UNKNOWN
Classifier: Programming Language :: Python :: 3
Classifier: License :: OSI Approved :: Apache Software License
Classifier: Operating System :: OS Independent
Requires-Python: >=3.6
